eldar_string_utils/__init__.py
eldar_string_utils/analysis.py
eldar_string_utils/filters.py
eldar_string_utils-1.0.0.dist-info/licenses/LICENSE
eldar_string_utils-1.0.0.dist-info/METADATA
eldar_string_utils-1.0.0.dist-info/WHEEL
eldar_string_utils-1.0.0.dist-info/top_level.txt
eldar_string_utils-1.0.0.dist-info/RECORD
