Metadata-Version: 2.4
Name: eldar-string-utils
Version: 1.0.0
Summary: A lightweight string processing and analysis library
Home-page: https://pypi.org/project/eldar-string-utils/
Author: Eldar Eliyev
Author-email: eldar@example.com
Classifier: Programming Language :: Python :: 3
Classifier: License :: OSI Approved :: MIT License
Classifier: Operating System :: OS Independent
Requires-Python: >=3.8
License-File: LICENSE
Dynamic: author
Dynamic: author-email
Dynamic: classifier
Dynamic: description
Dynamic: description-content-type
Dynamic: home-page
Dynamic: license-file
Dynamic: requires-python
Dynamic: summary
